CHANGES.rst
LICENSE.txt
MANIFEST.in
Makefile
README.rst
requirements.txt
setup.py
tests.py
vanity.py
vanity.egg-info/PKG-INFO
vanity.egg-info/SOURCES.txt
vanity.egg-info/dependency_links.txt
vanity.egg-info/entry_points.txt
vanity.egg-info/top_level.txt
vanity.egg-info/zip-safe