Metadata-Version: 1.1
Name: vanity
Version: 2.2.0
Summary: Get package download statistics from PyPI
Home-page: https://github.com/aclark4life/vanity
Author: Alex Clark
Author-email: aclark@aclark.net
License: GPL
Keywords: analytics python package index statistics
Platform: UNKNOWN
Classifier: Programming Language :: Python :: 2
Classifier: Programming Language :: Python :: 2.6
Classifier: Programming Language :: Python :: 2.7
Classifier: Programming Language :: Python :: 3
Classifier: Programming Language :: Python :: 3.2
Classifier: Programming Language :: Python :: 3.3
Classifier: Programming Language :: Python :: 3.4
Classifier: Programming Language :: Python :: 3.5
